LICENSE.txt
MANIFEST.in
README.textile
setup.cfg
setup.py
okcmd.egg-info/PKG-INFO
okcmd.egg-info/SOURCES.txt
okcmd.egg-info/dependency_links.txt
okcmd.egg-info/entry_points.txt
okcmd.egg-info/requires.txt
okcmd.egg-info/top_level.txt
src/__init__.py
src/arrow_fetcher.py