Metadata-Version: 1.1
Name: okcmd
Version: 1.2
Summary: A simple Python script for downloading your sent and received OkCupid messages.
Home-page: https://github.com/lehrblogger/OkCupid-Message-Downloader
Author: Steven Lehrburger
Author-email: lehrburger@gmail.com
License: UNKNOWN
Download-URL: https://github.com/lehrblogger/OkCupid-Message-Downloader/tarball/1.2
Keywords: okcupid,okc,okcmd,dating,archive,message,download,backup
Platform: UNKNOWN
Classifier: Development Status :: 4 - Beta
Classifier: License :: OSI Approved :: MIT License
Classifier: Programming Language :: Python :: 2.7
